rezina/__init__.py
rezina/backends/__init__.py
rezina/backends/base.py
rezina/backends/null.py
rezina/backends/resultwriteback.py
rezina/bin/__init__.py
rezina/bin/master.py
rezina/bin/rezinacml.py
rezina/bin/worker.py
rezina/service/__init__.py
rezina/service/database.py
rezina/service/log.py
rezina/service/manager.py
rezina/service/monitor.py
rezina/service/worker.py
rezina/tests/__init__.py
rezina/tests/test_master.py
rezina/tests/test_network.py
rezina/tests/test_typology.py
rezina/tests/test_udfutil.py
rezina/tests/test_worker.py
rezina/tests/workerspace/__init__.py
rezina/tests/workerspace/computenum.py
rezina/tests/workerspace/tb.py
rezina/tests/workerspace/tb1.py
rezina/tests/workerspace/udf.py
rezina/typology/__init__.py
rezina/typology/broker.py
rezina/typology/builder.py
rezina/typology/components.py
rezina/typology/typology.py
rezina/utils/__init__.py
rezina/utils/colorterminal.py
rezina/utils/daemon.py
rezina/utils/model.py
rezina/utils/network.py
rezina/utils/timeout.py
rezina/utils/udfutil.py
rezina/web/__init__.py
rezina/web/httpserver.py
rezina/web/urls.py
rezina/web/handlers/__init__.py
rezina/web/handlers/handler.py
rezina/web/www/404.html
rezina/web/www/app.38a1ea9d732a1ab0ecfa.css
rezina/web/www/app.38a1ea9d732a1ab0ecfa.css.map
rezina/web/www/app.38a1ea9d732a1ab0ecfa.js
rezina/web/www/app.38a1ea9d732a1ab0ecfa.js.map
rezina/web/www/favicon.ico
rezina/web/www/index.html
rezina/web/www/polyfills.38a1ea9d732a1ab0ecfa.js
rezina/web/www/polyfills.38a1ea9d732a1ab0ecfa.js.map
rezina/web/www/vendor.38a1ea9d732a1ab0ecfa.js
rezina/web/www/vendor.38a1ea9d732a1ab0ecfa.js.map
rezina/web/www/assets/MaterialIcons-Regular.012cf6a10129e2275d79d6adac7f3b02.woff
rezina/web/www/assets/MaterialIcons-Regular.570eb83859dc23dd0eec423a49e147fe.woff2
rezina/web/www/assets/MaterialIcons-Regular.a37b0c01c0baf1888ca812cc0508f6e2.ttf
rezina/web/www/assets/MaterialIcons-Regular.e79bfd88537def476913f3ed52f4f4b3.eot
rezina-0.1.1.dist-info/DESCRIPTION.rst
rezina-0.1.1.dist-info/METADATA
rezina-0.1.1.dist-info/RECORD
rezina-0.1.1.dist-info/WHEEL
rezina-0.1.1.dist-info/metadata.json
rezina-0.1.1.dist-info/top_level.txt
